growler/__init__.py
growler/__meta__.py
growler/application.py
growler/middleware_chain.py
growler/protocol.py
growler/router.py
growler/ext/__init__.py
growler/http/__init__.py
growler/http/errors.py
growler/http/methods.py
growler/http/parser.py
growler/http/protocol.py
growler/http/request.py
growler/http/responder.py
growler/http/response.py
growler/http/status.py
growler/middleware/__init__.py
growler/middleware/auth.py
growler/middleware/cookieparser.py
growler/middleware/logger.py
growler/middleware/renderer.py
growler/middleware/responsetime.py
growler/middleware/session.py
growler/middleware/static.py
growler/middleware/timer.py
growler/mw/__init__.py
growler/utils/__init__.py
growler/utils/event_manager.py
growler-0.8.0.dist-info/DESCRIPTION.rst
growler-0.8.0.dist-info/METADATA
growler-0.8.0.dist-info/RECORD
growler-0.8.0.dist-info/WHEEL
growler-0.8.0.dist-info/metadata.json
growler-0.8.0.dist-info/top_level.txt
growler_ext/__init__.py
