Metadata-Version: 2.0
Name: growler
Version: 0.8.0
Summary: A micro web-framework using asyncio coroutines and chained middleware.
Home-page: https://github.com/pyGrowler/Growler
Author: Andrew Kubera
Author-email: andrew.kubera@gmail.com
License: Apache v2.0
Download-URL: https://github.com/pyGrowler/growler/archive/v0.8.0.tar.gz
Platform: all
Classifier: Development Status :: 3 - Alpha
Classifier: Environment :: Web Environment
Classifier: Operating System :: OS Independent
Classifier: License :: OSI Approved :: Apache Software License
Classifier: Programming Language :: Python
Classifier: Programming Language :: Python :: 3
Classifier: Programming Language :: Python :: 3.4
Classifier: Programming Language :: Python :: 3.5
Classifier: Topic :: Internet :: WWW/HTTP
Classifier: Natural Language :: English
Requires-Dist: asyncio (>=3.4.3); python_version=="3.3"
Provides-Extra: jade
Requires-Dist: pyjade; extra == 'jade'
Provides-Extra: mako
Requires-Dist: growler-mako; extra == 'mako'
